wideo/__init__.py
wideo/admin_urls.py
wideo/apps.py
wideo/blocks.py
wideo/codecs.py
wideo/exceptions.py
wideo/ffmpeg.py
wideo/fields.py
wideo/forms.py
wideo/management/__init__.py
wideo/management/commands/__init__.py
wideo/management/commands/delete_orphan_uploaded_videos.py
wideo/management/commands/encode_videos.py
wideo/migrations/0001_initial.py
wideo/migrations/0002_lock.py
wideo/migrations/0003_uploadedvideochunk.py
wideo/migrations/0004_alter_video_upload.py
wideo/migrations/0005_alter_video_upload.py
wideo/migrations/__init__.py
wideo/models.py
wideo/permissions.py
wideo/signals.py
wideo/storage.py
wideo/tasks.py
wideo/templates/wideo/blocks/video.html
wideo/templates/wideo/forms/file.html
wideo/templates/wideo/forms/file_edit.html
wideo/templates/wideo/icons/video.svg
wideo/templates/wideo/preview/plyr_styles.html
wideo/templates/wideo/preview/video_source.html
wideo/templates/wideo/video.html
wideo/templates/wideo/videos/add.html
wideo/templates/wideo/videos/confirm_delete.html
wideo/templates/wideo/videos/edit.html
wideo/templates/wideo/videos/index.html
wideo/templates/wideo/videos/results.html
wideo/templates/wideo/videos/results_video.html
wideo/templatetags/__init__.py
wideo/templatetags/settings.py
wideo/views.py
wideo/wagtail_hooks.py
wideo/widgets.py
wideo-0.7.3.dist-info/METADATA
wideo-0.7.3.dist-info/WHEEL
wideo-0.7.3.dist-info/RECORD
