Metadata-Version: 2.4
Name: wideo
Version: 0.7.3
Summary: Add video goodness to your Wagtail website
License: WTFPL
Requires-Python: >=3.10,<4.0
Classifier: License :: Other/Proprietary License
Classifier: Programming Language :: Python :: 3
Classifier: Programming Language :: Python :: 3.10
Classifier: Programming Language :: Python :: 3.11
Classifier: Programming Language :: Python :: 3.12
Classifier: Programming Language :: Python :: 3.13
Classifier: Programming Language :: Python :: 3.14
Requires-Dist: celery
Requires-Dist: python-magic (>=0.4.27,<0.5.0)
Requires-Dist: wagtail
